{"Items":[{"Id":4467,"Name":"Another Tasks","Created":"\/Date(1433134800000-0500)\/","Estimate":4.0000,"Project":{"ResourceType":"Project","Id":49105,"Name":"TP3"},"User":{"ResourceType":"User","Kind":"User","Id":3721,"FirstName":"Volha","LastName":"Ikhelis","Login":"volha"}},{"Id":4465,"Name":"test","Created":"\/Date(1427691600000-0500)\/","Estimate":0.0000,"Project":{"ResourceType":"Project","Id":49105,"Name":"TP3"},"User":{"ResourceType":"User","Kind":"User","Id":40051,"FirstName":"Konstantin","LastName":"Krivlenia","Login":"konstantin"}},{"Id":4464,"Name":"test","Created":"\/Date(1428296400000-0500)\/","Estimate":3.0000,"Project":{"ResourceType":"Project","Id":49105,"Name":"TP3"},"User":{"ResourceType":"User","Kind":"User","Id":40051,"FirstName":"Konstantin","LastName":"Krivlenia","Login":"konstantin"}}]}