{"Next":"https://plan.tpondemand.com/api/v1/GeneralFollowers/?take=25&skip=25","Items":[{"Id":1,"General":{"ResourceType":"General","Id":49128,"Name":"Custom Graphic Reports MVF"},"User":{"ResourceType":"User","Kind":"User","Id":3,"FirstName":"Michael","LastName":"Dubakov","Login":"firefalcon"}},{"Id":2,"General":{"ResourceType":"General","Id":86615,"Name":"Epics MVF"},"User":{"ResourceType":"User","Kind":"User","Id":3,"FirstName":"Michael","LastName":"Dubakov","Login":"firefalcon"}},{"Id":3,"General":{"ResourceType":"General","Id":68223,"Name":"Team Workflow MVF"},"User":{"ResourceType":"User","Kind":"User","Id":3,"FirstName":"Michael","LastName":"Dubakov","Login":"firefalcon"}},{"Id":8,"General":{"ResourceType":"General","Id":54570,"Name":"Easy States setup MVF"},"User":{"ResourceType":"User","Kind":"User","Id":3,"FirstName":"Michael","LastName":"Dubakov","Login":"firefalcon"}},{"Id":27,"General":{"ResourceType":"General","Id":54087,"Name":"Follow"},"User":{"ResourceType":"User","Kind":"User","Id":44687,"FirstName":"Steve","LastName":"Mazurkiewicz","Login":"steve"}},{"Id":28,"General":{"ResourceType":"General","Id":86615,"Name":"Epics MVF"},"User":{"ResourceType":"User","Kind":"User","Id":44687,"FirstName":"Steve","LastName":"Mazurkiewicz","Login":"steve"}},{"Id":38,"General":{"ResourceType":"General","Id":88773,"Name":"Sequence contains more than one element - on the board with People as lane and filter by teamiteration"},"User":{"ResourceType":"User","Kind":"User","Id":3362,"FirstName":"Nadia","LastName":"Bulynia","Login":"nadia"}},{"Id":39,"General":{"ResourceType":"General","Id":88272,"Name":"test Solution Gallery"},"User":{"ResourceType":"User","Kind":"User","Id":33666,"FirstName":"Egor","LastName":"Sviridenko","Login":"Egor"}},{"Id":40,"General":{"ResourceType":"General","Id":88790,"Name":"как убрать колонку ToDo или Open"},"User":{"ResourceType":"User","Kind":"User","Id":57508,"FirstName":"Natalia","LastName":"Dulko","Login":"dulko"}},{"Id":41,"General":{"ResourceType":"General","Id":88120,"Name":"Display prorate on pending order cnanged"},"User":{"ResourceType":"User","Kind":"User","Id":22518,"FirstName":"Sergey","LastName":"Ryabtsev","Login":"Ryabtsev"}},{"Id":46,"General":{"ResourceType":"General","Id":69087,"Name":"au server!"},"User":{"ResourceType":"User","Kind":"User","Id":62523,"FirstName":"Dima","LastName":"Yackevich","Login":"Dima"}},{"Id":47,"General":{"ResourceType":"General","Id":73317,"Name":"Puppet provision"},"User":{"ResourceType":"User","Kind":"User","Id":62523,"FirstName":"Dima","LastName":"Yackevich","Login":"Dima"}},{"Id":48,"General":{"ResourceType":"General","Id":88861,"Name":"Errors when adding and opening new bug..."},"User":{"ResourceType":"User","Kind":"User","Id":57508,"FirstName":"Natalia","LastName":"Dulko","Login":"dulko"}},{"Id":49,"General":{"ResourceType":"General","Id":88707,"Name":"State info should be more detailed"},"User":{"ResourceType":"User","Kind":"User","Id":14483,"FirstName":"Alex","LastName":"Fomin","Login":"fomin"}},{"Id":50,"General":{"ResourceType":"General","Id":88706,"Name":"Entity ID and some formatting fixes"},"User":{"ResourceType":"User","Kind":"User","Id":66297,"FirstName":"Irina","LastName":"Gurina","Login":"irina.gurina@targetprocess.com"}},{"Id":51,"General":{"ResourceType":"General","Id":87709,"Name":"Track Author of modification"},"User":{"ResourceType":"User","Kind":"User","Id":66297,"FirstName":"Irina","LastName":"Gurina","Login":"irina.gurina@targetprocess.com"}},{"Id":54,"General":{"ResourceType":"General","Id":84637,"Name":"Cross-project Releases MVF"},"User":{"ResourceType":"User","Kind":"User","Id":3,"FirstName":"Michael","LastName":"Dubakov","Login":"firefalcon"}},{"Id":55,"General":{"ResourceType":"General","Id":54087,"Name":"Follow"},"User":{"ResourceType":"User","Kind":"User","Id":3,"FirstName":"Michael","LastName":"Dubakov","Login":"firefalcon"}},{"Id":56,"General":{"ResourceType":"General","Id":75637,"Name":"Hierarchical Test Plans MMF"},"User":{"ResourceType":"User","Kind":"User","Id":3,"FirstName":"Michael","LastName":"Dubakov","Login":"firefalcon"}},{"Id":57,"General":{"ResourceType":"General","Id":89006,"Name":"Change subject in mention email to: You were mentioned in a comment on User Story #15065"},"User":{"ResourceType":"User","Kind":"User","Id":3,"FirstName":"Michael","LastName":"Dubakov","Login":"firefalcon"}},{"Id":58,"General":{"ResourceType":"General","Id":88921,"Name":"Long entity name overlay Follow button"},"User":{"ResourceType":"User","Kind":"User","Id":64533,"FirstName":"Tania","LastName":"Leonchenko","Login":"tania"}},{"Id":82,"General":{"ResourceType":"General","Id":88030,"Name":"Show epic as a card (color, basic properties)"},"User":{"ResourceType":"User","Kind":"User","Id":52639,"FirstName":"Ruslan","LastName":"Girichev","Login":"ruslan"}},{"Id":83,"General":{"ResourceType":"General","Id":54570,"Name":"Easy States setup MVF"},"User":{"ResourceType":"User","Kind":"User","Id":44687,"FirstName":"Steve","LastName":"Mazurkiewicz","Login":"steve"}},{"Id":84,"General":{"ResourceType":"General","Id":49128,"Name":"Custom Graphic Reports MVF"},"User":{"ResourceType":"User","Kind":"User","Id":44687,"FirstName":"Steve","LastName":"Mazurkiewicz","Login":"steve"}},{"Id":85,"General":{"ResourceType":"General","Id":68223,"Name":"Team Workflow MVF"},"User":{"ResourceType":"User","Kind":"User","Id":44687,"FirstName":"Steve","LastName":"Mazurkiewicz","Login":"steve"}}]}